{
    "Actor":{
        "0":0.677184466,
        "1":0.6975806452,
        "2":0.6544117647,
        "3":0.6713917526,
        "4":0.6863309353
    },
    "Activity":{
        "0":0.7936507937,
        "1":0.807860262,
        "2":0.7823408624,
        "3":0.7651821862,
        "4":0.8169336384
    },
    "Activity Data":{
        "0":0.75,
        "1":0.7514925373,
        "2":0.6967272727,
        "3":0.6942266572,
        "4":0.7540849673
    },
    "Further Specification":{
        "0":0.7857142857,
        "1":0.9323308271,
        "2":0.8919753086,
        "3":0.875,
        "4":0.864978903
    },
    "XOR Gateway":{
        "0":0.7384615385,
        "1":0.7580645161,
        "2":0.8333333333,
        "3":0.7678571429,
        "4":0.724137931
    },
    "Condition Specification":{
        "0":0.8395833333,
        "1":0.8662790698,
        "2":0.8349056604,
        "3":0.8596491228,
        "4":0.9033149171
    },
    "AND Gateway":{
        "0":1.0,
        "1":1.0,
        "2":1.0,
        "3":1.0,
        "4":1.0
    },
    "All":{
        "0":0.7347789825,
        "1":0.7620967742,
        "2":0.7177211566,
        "3":0.7209036317,
        "4":0.7546296296
    }
}